similarity_search/__init__.py
similarity_search/constants.py
similarity_search/model.py
similarity_search/search_engine.py
similarity_search/db/__init__.py
similarity_search/db/db_base.py
similarity_search/db/sqllite.py
similarity_search/engine/__init__.py
similarity_search/engine/engine_base.py
similarity_search/engine/engine_registry.py
similarity_search/engine/faiss_engine.py
similarity_search/loaders/__init__.py
similarity_search/loaders/loader_base.py
similarity_search/loaders/image/__init__.py
similarity_search/loaders/image/csv_loader.py
similarity_search/loaders/image/directory_loader.py
similarity_search/loaders/image/image_loader_base.py
similarity_search/loaders/tabular/__init__.py
similarity_search/losses/__init__.py
similarity_search/losses/cosine.py
similarity_search/losses/loss_base.py
similarity_search/losses/loss_registry.py
similarity_search/plotting/__init__.py
similarity_search/plotting/image_plotter.py
similarity_search/psf/__init__.py
similarity_search/psf/kl_divergence_filter.py
similarity_search/psf/post_search_filter.py
similarity_search-0.0.1rc1.dist-info/LICENSE
similarity_search-0.0.1rc1.dist-info/METADATA
similarity_search-0.0.1rc1.dist-info/WHEEL
similarity_search-0.0.1rc1.dist-info/top_level.txt
similarity_search-0.0.1rc1.dist-info/RECORD
