Metadata-Version: 2.2
Name: similarity_search
Version: 0.0.1rc1
Summary: N/A
Home-page: https://github.com/pavanreddy-ml/similarity-search
Author: Pavan Reddy
Author-email: preddy.osdev@gmail.com
License: MIT
Classifier: Programming Language :: Python :: 3
Classifier: License :: OSI Approved :: MIT License
Classifier: Operating System :: OS Independent
Requires-Python: >=3.9
License-File: LICENSE
Requires-Dist: pytest
Requires-Dist: pytest-cov
Requires-Dist: flake8
Requires-Dist: mypy
Requires-Dist: Sphinx
Provides-Extra: testing
Requires-Dist: pytest; extra == "testing"
Requires-Dist: pytest-cov; extra == "testing"
Dynamic: requires-dist
